src/clock_divider.v
module clock_divider
  // Parameters section
  #(parameter WIDTH = 8)
(
  // Ports section
  input clk_in, nrst,
  input [WIDTH-1:0] scale,
  output clk_out 
);
  integer count ; // counter
  integer CONST = 2 ;// 200000 ; // CONSTANT to multiply the 'scale'
  reg  [WIDTH-1:0] scale_reg ; // register to save the scale_reg when reset is triggered
  reg  [15:0] true_scale ; // the 'true' scale defined as 'scale_reg * CONST'
  reg signal_clk_out ; // register to save the clk_out and send it to this port

  initial begin
      signal_clk_out = 0 ;
      count = 0 ;   
      scale_reg [WIDTH-1:0] = scale ;
      signal_clk_out = 0 ;
  end

  always @(negedge nrst or posedge clk_in) begin 
    if (!nrst) begin
      signal_clk_out <= 0 ;
      count <= 0 ;
      scale_reg <=  scale; // set the scale to a internal register scale_reg when update_scale is triggered
      true_scale <= scale*CONST ; // update the true scale
    end
    else begin
        if (count == (true_scale/2 - 1)) begin
          signal_clk_out <= ~signal_clk_out ; // toggle the signal_clk_out then 'count == true_scale'
          count <= 0 ;
        end else begin 
          count <= count + 1 ;
        end
    end 
  end



  assign clk_out = (true_scale == 0) ? clk_in : signal_clk_out ; // if the true_scale is zero, the clk_in is buffered to the output

endmodule

src/tb_clock_divider.v
`include "./clock_divider.v"

module tb_clock_divider;
    // Params
  localparam WIDTH=8;  
  localparam CLK_PERIOD=10;  

  // Regs and wires
  reg clk_in, nrst;
  reg [WIDTH-1:0] scale;
  wire clk_out;

    // Instantiating the clock_divider
  clock_divider 
  #(
     .WIDTH ( WIDTH )
  )
  clock_divider_0
  (
  .clk_in   (clk_in), 
  .nrst     (nrst),
  .scale    (scale),
  .clk_out  (clk_out)
  );

initial begin 
    $display("Dumping vars");
    $dumpfile("tb_clock_divider.vcd");
    $dumpvars(0, clock_divider_0);

    $display("Initializing...");
    nrst = 1;
    scale = 3;
    clk_in = 0; //initializing the clock 
    # 11
    nrst = 0; // reseting the clock_divider
    # 2
    nrst = 1;
    # 1
    scale = 6;
    # 150
    nrst = 0;
    # 1
    nrst = 1;
end

// Clock signal
always begin 
    # (CLK_PERIOD/2) clk_in = ~ clk_in;
end

// Finish
always begin 
    # (40*CLK_PERIOD)
    $finish;
end
endmodule

src/tb_clock_divider.vcd
$date
	Tue Dec 12 23:30:30 2023
$end
$version
	Icarus Verilog
$end
$timescale
	1s
$end
$scope module tb_clock_divider $end
$scope module clock_divider_0 $end
$var wire 1 ! clk_in $end
$var wire 1 " nrst $end
$var wire 8 # scale [7:0] $end
$var wire 1 $ clk_out $end
$var parameter 32 % WIDTH $end
$var reg 8 & scale_reg [7:0] $end
$var reg 1 ' signal_clk_out $end
$var reg 16 ( true_scale [15:0] $end
$var integer 32 ) CONST [31:0] $end
$var integer 32 * count [31:0] $end
$upscope $end
$upscope $end
$enddefinitions $end
$comment Show the parameter values. $end
$dumpall
b1000 %
$end
#0
$dumpvars
b0 *
b10 )
bx (
0'
bx &
0$
b11 #
1"
0!
$end
#5
b1 *
x$
1!
#10
0$
0!
#11
b110 (
b11 &
b0 *
0"
#13
1"
#14
b110 #
#15
b1 *
1!
#20
0!
#25
b10 *
1!
#30
0!
#35
1$
b0 *
1'
1!
#40
0!
#45
b1 *
1!
#50
0!
#55
b10 *
1!
#60
0!
#65
0$
b0 *
0'
1!
#70
0!
#75
b1 *
1!
#80
0!
#85
b10 *
1!
#90
0!
#95
1$
b0 *
1'
1!
#100
0!
#105
b1 *
1!
#110
0!
#115
b10 *
1!
#120
0!
#125
0$
b0 *
0'
1!
#130
0!
#135
b1 *
1!
#140
0!
#145
b10 *
1!
#150
0!
#155
1$
b0 *
1'
1!
#160
0!
#164
0$
b1100 (
b110 &
0'
0"
#165
b1 *
1"
1!
#170
0!
#175
b10 *
1!
#180
0!
#185
b11 *
1!
#190
0!
#195
b100 *
1!
#200
0!
#205
b101 *
1!
#210
0!
#215
1$
b0 *
1'
1!
#220
0!
#225
b1 *
1!
#230
0!
#235
b10 *
1!
#240
0!
#245
b11 *
1!
#250
0!
#255
b100 *
1!
#260
0!
#265
b101 *
1!
#270
0!
#275
0$
b0 *
0'
1!
#280
0!
#285
b1 *
1!
#290
0!
#295
b10 *
1!
#300
0!
#305
b11 *
1!
#310
0!
#315
b100 *
1!
#320
0!
#325
b101 *
1!
#330
0!
#335
1$
b0 *
1'
1!
#340
0!
#345
b1 *
1!
#350
0!
#355
b10 *
1!
#360
0!
#365
b11 *
1!
#370
0!
#375
b100 *
1!
#380
0!
#385
b101 *
1!
#390
0!
#395
0$
b0 *
0'
1!
